canvas_workflow_kit/__init__.py
canvas_workflow_kit/action.py
canvas_workflow_kit/api.py
canvas_workflow_kit/builtin_cqms/__init__.py
canvas_workflow_kit/builtin_cqms/ccp001v1_symptomatic_surveillance.py
canvas_workflow_kit/builtin_cqms/ccp002v1_high_risk_outreach.py
canvas_workflow_kit/builtin_cqms/ccp003v1_hypertension.py
canvas_workflow_kit/builtin_cqms/ccp004v1_diabetes.py
canvas_workflow_kit/builtin_cqms/ccp005v1_asthma.py
canvas_workflow_kit/builtin_cqms/cms122v6_diabetes_hemoglobin_a1c_poor_control.py
canvas_workflow_kit/builtin_cqms/cms123v6_diabetes_foot_exam.py
canvas_workflow_kit/builtin_cqms/cms125v6_breast_cancer_screening.py
canvas_workflow_kit/builtin_cqms/cms130v6_colorectal_cancer_screening.py
canvas_workflow_kit/builtin_cqms/cms131v6_diabetes_eye_exam.py
canvas_workflow_kit/builtin_cqms/cms134v6_diabetes_medical_attention_for_nephropathy.py
canvas_workflow_kit/builtin_cqms/cms138v6_preventive_care_and_screening_tobacco_use_screening_and_cessation_intervention.py
canvas_workflow_kit/builtin_cqms/cms138v6p1.py
canvas_workflow_kit/builtin_cqms/cms138v6p2.py
canvas_workflow_kit/builtin_cqms/customer_scan_complex_case_management_referral.py
canvas_workflow_kit/builtin_cqms/customer_scan_dementia_assessment.py
canvas_workflow_kit/builtin_cqms/customer_scan_hcc_suspect_alert.py
canvas_workflow_kit/builtin_cqms/customer_scan_mood_disorder.py
canvas_workflow_kit/builtin_cqms/customer_scan_physical_activity_intervention.py
canvas_workflow_kit/builtin_cqms/customer_scan_urinary_symptoms_assessment.py
canvas_workflow_kit/builtin_cqms/diabetes_quality_measure.py
canvas_workflow_kit/builtin_cqms/future/cms138v6_preventive_care_and_screening_tobacco_use_screening_and_cessation_intervention.py
canvas_workflow_kit/builtin_cqms/future/cms139v6_falls_screening_for_future_fall_risk.py
canvas_workflow_kit/builtin_cqms/future/cms147v7_preventive_care_and_screening_influenza_immunization.py
canvas_workflow_kit-0.6.11.dist-info/entry_points.txt
canvas_workflow_kit-0.6.11.dist-info/WHEEL
canvas_workflow_kit-0.6.11.dist-info/METADATA
canvas_workflow_kit-0.6.11.dist-info/RECORD
