Metadata-Version: 2.1
Name: canvas-workflow-kit
Version: 0.6.11
Summary: Development kit to empower customization of your Canvas instance
Author: Canvas Team
Author-email: engineering@canvasmedical.com
Requires-Python: >=3.7,<4.0
Classifier: Programming Language :: Python :: 3
Classifier: Programming Language :: Python :: 3.10
Classifier: Programming Language :: Python :: 3.7
Classifier: Programming Language :: Python :: 3.8
Classifier: Programming Language :: Python :: 3.9
Requires-Dist: arrow
Requires-Dist: cached-property (>=1.5.0,<1.6.0)
Requires-Dist: click
Requires-Dist: memoization (>=0.4.0,<0.5.0)
Requires-Dist: python-decouple (>=3.0.0,<4.0.0)
Requires-Dist: requests (>=2.0.0,<3.0.0)
